{
  "task": "TASK-MB-007",
  "run_at": "2026-04-23T11:23:49Z",
  "params": {
    "sl_atr_mult": 1.5,
    "tp_atr_mult": 3.0,
    "max_hold_bars": 48,
    "cost_one_side_pct": 0.06999999999999999,
    "vol_ma_period": 20
  },
  "symbols": {
    "BTCUSDT": {
      "total_trades": 510,
      "daily_avg": 0.621,
      "win_rate_pct": 37.45,
      "avg_win_atr": 2.4508,
      "avg_loss_atr": -1.6665,
      "ev_per_trade_atr": -0.1245,
      "profit_factor": 0.8509,
      "mdd_pct": 66.1617,
      "tp_rate_pct": 31.96,
      "sl_rate_pct": 59.8,
      "timeout_rate_pct": 8.24,
      "by_year": {
        "2024": {
          "total_trades": 223,
          "win_rate_pct": 42.6,
          "ev_per_trade_atr": 0.0433,
          "profit_factor": 1.0056
        },
        "2025": {
          "total_trades": 226,
          "win_rate_pct": 34.07,
          "ev_per_trade_atr": -0.2361,
          "profit_factor": 0.7522
        },
        "2026_q1": {
          "total_trades": 61,
          "win_rate_pct": 31.15,
          "ev_per_trade_atr": -0.3247,
          "profit_factor": 0.6766
        }
      }
    },
    "ETHUSDT": {
      "total_trades": 515,
      "daily_avg": 0.627,
      "win_rate_pct": 35.34,
      "avg_win_atr": 2.6208,
      "avg_loss_atr": -1.618,
      "ev_per_trade_atr": -0.12,
      "profit_factor": 0.8031,
      "mdd_pct": 121.0224,
      "tp_rate_pct": 31.26,
      "sl_rate_pct": 62.91,
      "timeout_rate_pct": 5.83,
      "by_year": {
        "2024": {
          "total_trades": 227,
          "win_rate_pct": 34.8,
          "ev_per_trade_atr": -0.1354,
          "profit_factor": 0.7873
        },
        "2025": {
          "total_trades": 239,
          "win_rate_pct": 37.24,
          "ev_per_trade_atr": -0.0492,
          "profit_factor": 0.8781
        },
        "2026_q1": {
          "total_trades": 49,
          "win_rate_pct": 28.57,
          "ev_per_trade_atr": -0.3941,
          "profit_factor": 0.5521
        }
      }
    }
  },
  "vs_mb003": {
    "ev_improved": false,
    "sl_rate_improved": true,
    "win_rate_improved": false
  },
  "verdict": "EV_NEGATIVE",
  "note": "EV_NEGATIVE -- F 안전장치 집행 대상. 의장에게 즉시 보고 후 대기."
}